Metadata-Version: 2.1
Name: py3Solr
Version: 0.1.0
Summary: Python3 client for Apache Solr
Home-page: https://github.com/wbq813/py3Solr/
Author: wbq813
Author-email: wbq813@foxmail.com
License: MIT
Project-URL: blog, http://codeyourlife.cn
Platform: UNKNOWN
Classifier: Development Status :: 4 - Beta
Classifier: Intended Audience :: Developers
Classifier: License :: OSI Approved :: MIT License
Classifier: Operating System :: OS Independent
Classifier: Programming Language :: Python
Classifier: Topic :: Internet :: WWW/HTTP :: Indexing/Search
Classifier: Programming Language :: Python :: 3
Requires-Python: >=3.3
Provides-Extra: solrCloud
